pymax/__init__.py
pymax/core.py
pymax/crud.py
pymax/exceptions.py
pymax/files.py
pymax/filters.py
pymax/formatter.py
pymax/formatting.py
pymax/interfaces.py
pymax/models.py
pymax/navigation.py
pymax/payloads.py
pymax/protocols.py
pymax/types.py
pymax/utils.py
pymax/mixins/__init__.py
pymax/mixins/auth.py
pymax/mixins/channel.py
pymax/mixins/group.py
pymax/mixins/handler.py
pymax/mixins/message.py
pymax/mixins/scheduler.py
pymax/mixins/self.py
pymax/mixins/socket.py
pymax/mixins/telemetry.py
pymax/mixins/user.py
pymax/mixins/websocket.py
pymax/static/constant.py
pymax/static/enum.py
maxapi_python-1.2.5.dist-info/METADATA
maxapi_python-1.2.5.dist-info/WHEEL
maxapi_python-1.2.5.dist-info/licenses/LICENSE
maxapi_python-1.2.5.dist-info/RECORD
