Metadata-Version: 2.4
Name: maxapi-python
Version: 1.2.5
Summary: Python wrapper для API мессенджера Max
Project-URL: Homepage, https://github.com/MaxApiTeam/PyMax
Project-URL: Repository, https://github.com/MaxApiTeam/PyMax
Project-URL: Issues, https://github.com/MaxApiTeam/PyMax/issues
Author-email: ink <mail@gmail.com>
License-Expression: MIT
License-File: LICENSE
Keywords: api,max,messenger,websocket,wrapper
Classifier: Operating System :: OS Independent
Classifier: Programming Language :: Python :: 3
Requires-Python: >=3.10
Requires-Dist: aiofiles>=24.1.0
Requires-Dist: aiohttp>=3.12.15
Requires-Dist: lz4>=4.4.4
Requires-Dist: msgpack>=1.1.1
Requires-Dist: qrcode>=8.2
Requires-Dist: sqlmodel>=0.0.24
Requires-Dist: ua-generator>=2.0.19
Requires-Dist: websockets>=15.0
Provides-Extra: test
Requires-Dist: flake8; extra == 'test'
Requires-Dist: mypy; extra == 'test'
Requires-Dist: pytest-asyncio>=0.24.0; extra == 'test'
Requires-Dist: pytest-cov>=5.0.0; extra == 'test'
Requires-Dist: pytest-timeout>=2.1.0; extra == 'test'
Requires-Dist: pytest>=8.0.0; extra == 'test'
